rewrite/__init__.py
rewrite/assessment.py
rewrite/autodoc_example.py
rewrite/blankpage.py
rewrite/course.py
rewrite/image.py
rewrite/mathlib.py
rewrite/message.py
rewrite/nameline.py
rewrite/newpage.py
rewrite/pdfpages.py
rewrite/problem.py
rewrite/problemset.py
rewrite/publisher.py
rewrite/release.py
rewrite/schedule.py
rewrite/term.py
rewrite/usertex.py
rewrite/tex/__init__.py
rewrite/tex/assessment.py
rewrite/tex/basicformat.py
rewrite/tex/blankpage.py
rewrite/tex/bools.py
rewrite/tex/custom.py
rewrite/tex/image.py
rewrite/tex/math.py
rewrite/tex/message.py
rewrite/tex/nameline.py
rewrite/tex/newpage.py
rewrite/tex/pdfpages.py
rewrite/tex/problem.py
rewrite/tex/problemset.py
rewrite/tex/pyvars.py
rewrite/tex/texlist.py
rewrite/tex/usertex.py
rewrite/tex/utils.py
rewrite-0.0.1.dev5.data/scripts/newproblem
rewrite-0.0.1.dev5.dist-info/LICENSE.md
rewrite-0.0.1.dev5.dist-info/METADATA
rewrite-0.0.1.dev5.dist-info/WHEEL
rewrite-0.0.1.dev5.dist-info/top_level.txt
rewrite-0.0.1.dev5.dist-info/RECORD
