Metadata-Version: 2.1
Name: rewrite
Version: 0.0.1.dev5
Summary: ReWrite is a Python package for generating PDF documents via LaTeX. The goal of this project is to allow instructors to recreate course documents that must change in routine ways every time the course is offered. My vision is for ReWrite to support the creating of randomizable math problems and assessments without extensive programming knowledge.
Home-page: https://pypi.org/project/rewrite/
Author: Michael Barnard
Author-email: mbarnard10@ivytech.edu
License: MIT
Platform: UNKNOWN
Classifier: Programming Language :: Python :: 3
Classifier: License :: OSI Approved :: MIT License
Classifier: Operating System :: OS Independent
